clovers_leafgame/__init__.py
clovers_leafgame/config.py
clovers_leafgame/core/clovers.py
clovers_leafgame/core/data.py
clovers_leafgame/item.py
clovers_leafgame/main.py
clovers_leafgame/manager.py
clovers_leafgame/modules/account/__init__.py
clovers_leafgame/modules/account/config.py
clovers_leafgame/modules/game/__init__.py
clovers_leafgame/modules/game/collection/action.py
clovers_leafgame/modules/game/collection/blackjack.py
clovers_leafgame/modules/game/collection/bohemia_dice.py
clovers_leafgame/modules/game/collection/buckshot_roulette.py
clovers_leafgame/modules/game/collection/cantrell.py
clovers_leafgame/modules/game/collection/dice.py
clovers_leafgame/modules/game/collection/fortress/core.py
clovers_leafgame/modules/game/collection/horse_race/__init__.py
clovers_leafgame/modules/game/collection/horse_race/config.py
clovers_leafgame/modules/game/collection/horse_race/event_library/Stand.json
clovers_leafgame/modules/game/collection/horse_race/event_library/“日常，真的很日常”.json
clovers_leafgame/modules/game/collection/horse_race/event_library/克苏鲁.json
clovers_leafgame/modules/game/collection/horse_race/event_library/基础事件.json
clovers_leafgame/modules/game/collection/horse_race/event_library/复刻经典事件集合v1.json
clovers_leafgame/modules/game/collection/horse_race/event_library/崩坏集合v1.json
clovers_leafgame/modules/game/collection/horse_race/event_library/群友日常.json
clovers_leafgame/modules/game/collection/horse_race/event_library/芜湖事件合集.json
clovers_leafgame/modules/game/collection/horse_race/event_library/赫尔事件集v1.json
clovers_leafgame/modules/game/collection/horse_race/event_library/赫尔的赛马场事件簿.json
clovers_leafgame/modules/game/collection/horse_race/horse.py
clovers_leafgame/modules/game/collection/horse_race/start.py
clovers_leafgame/modules/game/collection/horse_race_game.py
clovers_leafgame/modules/game/collection/poker_battle.py
clovers_leafgame/modules/game/collection/russian_roulette.py
clovers_leafgame/modules/game/collection/western_duel.py
clovers_leafgame-0.2.4.dist-info/LICENSE
clovers_leafgame-0.2.4.dist-info/METADATA
clovers_leafgame-0.2.4.dist-info/WHEEL
clovers_leafgame-0.2.4.dist-info/RECORD
