Metadata-Version: 2.3
Name: clovers-leafgame
Version: 0.2.4
Summary: 
Author: KarisAya
Author-email: 1048827424@qq.com
Requires-Python: >=3.12,<4.0
Classifier: Programming Language :: Python :: 3
Classifier: Programming Language :: Python :: 3.12
Classifier: Programming Language :: Python :: 3.13
Requires-Dist: clovers (>=0.3.4,<0.4.0)
Requires-Dist: clovers-apscheduler (>=0.2.0,<0.3.0)
Requires-Dist: clovers-utils[all] (>=0.2.3,<0.3.0)
Requires-Dist: matplotlib (>=3.10.0,<4.0.0)
Requires-Dist: mplfinance (>=0.12.10b0,<0.13.0)
Requires-Dist: pydantic (>=2.10.6,<3.0.0)
